figio/__init__.py
figio/command_line.py
figio/composite.py
figio/cross_correlation.py
figio/factory.py
figio/figure.py
figio/hello.py
figio/histogram.py
figio/parse.py
figio/schema.py
figio/utility.py
figio/xybase.py
figio/xymodel.py
figio/xytypes.py
figio/xyview.py
figio/yml_to_dict.py
figio-0.0.8.dist-info/licenses/LICENSE
figio-0.0.8.dist-info/METADATA
figio-0.0.8.dist-info/WHEEL
figio-0.0.8.dist-info/entry_points.txt
figio-0.0.8.dist-info/top_level.txt
figio-0.0.8.dist-info/RECORD
